craydel_database_wrapper/__init__.py
craydel_database_wrapper/core.py
craydel_database_wrapper/services/chat_summarizer/llm_chat_summarizer.py
craydel_database_wrapper/services/clickhouse_db/db_interactions.py
craydel_database_wrapper/services/clickhouse_db/types.py
craydel_database_wrapper/utils/logging_trait.py
craydel_database_wrapper-0.0.7.dist-info/licenses/LICENSE
craydel_database_wrapper-0.0.7.dist-info/METADATA
craydel_database_wrapper-0.0.7.dist-info/WHEEL
craydel_database_wrapper-0.0.7.dist-info/top_level.txt
craydel_database_wrapper-0.0.7.dist-info/RECORD
