Metadata-Version: 2.4
Name: craydel-database-wrapper
Version: 0.0.7
Summary: ClickHouse chat storage + optional summarizer (bring-your-own-LLM)
License: MIT
Classifier: Programming Language :: Python :: 3
Classifier: Operating System :: OS Independent
Requires-Python: >=3.9
License-File: LICENSE
Dynamic: license-file
